aioice/__init__.py
aioice/about.py
aioice/candidate.py
aioice/ice.py
aioice/mdns.py
aioice/py.typed
aioice/stun.py
aioice/turn.py
aioice/utils.py
aioice-0.9.0.dist-info/LICENSE
aioice-0.9.0.dist-info/METADATA
aioice-0.9.0.dist-info/WHEEL
aioice-0.9.0.dist-info/top_level.txt
aioice-0.9.0.dist-info/RECORD
